howiml/__init__.py
howiml/core.py
howiml/core_configs.py
howiml/core_stateful.py
howiml/core_stateless.py
howiml/utils/analysis.py
howiml/utils/configs.py
howiml/utils/metrics.py
howiml/utils/modelFuncs.py
howiml/utils/models.py
howiml/utils/optimizes.py
howiml/utils/plots.py
howiml/utils/prints.py
howiml/utils/utilities.py
howiml-1.0.0.dist-info/LICENSE
howiml-1.0.0.dist-info/METADATA
howiml-1.0.0.dist-info/WHEEL
howiml-1.0.0.dist-info/top_level.txt
howiml-1.0.0.dist-info/RECORD
