Metadata-Version: 2.1
Name: howiml
Version: 1.0.0
Summary: A top-level machine learning framework
Home-page: https://github.com/hermanwh/howi-ml
Author: Herman Wika Horn
Author-email: hermanwh@hotmail.com
License: UNKNOWN
Platform: UNKNOWN
Classifier: Programming Language :: Python :: 3
Classifier: License :: OSI Approved :: Apache Software License
Classifier: Operating System :: OS Independent
Requires-Python: >=3.6, <3.7
Requires-Dist: Keras (<2.3.2,>=2.3.1)
Requires-Dist: matplotlib (<3.2.1,>=3.2.0)
Requires-Dist: numpy (<1.18.2,>=1.18.1)
Requires-Dist: pandas (<0.25.4,>=0.25.3)
Requires-Dist: pandas-profiling (<2.5.1,>=2.5.0)
Requires-Dist: prettytable (<0.7.3,>=0.7.2)
Requires-Dist: scikit-learn (<0.22.3,>=0.22.2)
Requires-Dist: seaborn (<0.10.1,>=0.10.0)
Requires-Dist: tensorflow (<2.1.1,>=2.1.0)
Requires-Dist: notebook (<6.0.4,>=6.0.3)
